{
  "kind": "collectionType",
  "collectionName": "activities",
  "info": {
    "name": "Activity",
    "description": ""
  },
  "options": {
    "increments": true,
    "timestamps": true,
    "draftAndPublish": false
  },
  "attributes": {
    "lesson_module": {
      "via": "activities",
      "model": "lesson-module"
    },
    "number": {
      "type": "biginteger",
      "required": true
    },
    "template": {
      "type": "text",
      "required": true
    },
    "blocks": {
      "collection": "block"
    },
    "description": {
      "type": "text"
    },
    "StandardS": {
      "type": "string"
    },
    "images": {
      "type": "text"
    },
    "link": {
      "type": "string",
      "required": false
    },
    "learning_components": {
      "via": "activities",
      "collection": "learning-components"
    },
    "activity_template": {
      "type": "text",
      "required": false
    }
  }
}
